LICENSE
README.md
setup.cfg
setup.py
moneyworks/__init__.py
moneyworks/email.py
moneyworks/moneyworks.py
moneyworks/transaction.py
moneyworks.egg-info/PKG-INFO
moneyworks.egg-info/SOURCES.txt
moneyworks.egg-info/dependency_links.txt
moneyworks.egg-info/requires.txt
moneyworks.egg-info/top_level.txt