Metadata-Version: 1.1
Name: moneyworks
Version: 1.1.0
Summary: A python API for Cognito Moneyworks accounting software
Home-page: http://github.com/ari/moneyworks-cli/
Author: Aristedes Maniatis
Author-email: ari@ish.com.au
License: APL2
Keywords: api moneyworks accounting
Platform: UNKNOWN
Classifier: Development Status :: 5 - Production/Stable
Classifier: Intended Audience :: Developers
Classifier: Topic :: Software Development :: Libraries :: Python Modules
Classifier: License :: OSI Approved :: Apache Software License
Classifier: Programming Language :: Python :: 3
Classifier: Programming Language :: Python :: 3.4
Classifier: Programming Language :: Python :: 3.5
Classifier: Programming Language :: Python :: 3.6
